{
  "person": {
    "name": "Hayden Thomas",
    "dob": "01/24/1983",
    "phone": "(464) 597-5013",
    "address": [
      "765 Oak St",
      "Springfield, RI 87265"
    ],
    "sex": "Other"
  },
  "meta": {
    "mrn": "390801-97",
    "physician": "Dr. Garcia",
    "emergency_contact": "Jamie Thomas",
    "emergency_phone": "(321) 299-5002",
    "smoker": false,
    "diabetic": true,
    "allergies": [
      "None Known"
    ],
    "symptoms": [
      5
    ]
  },
  "type": "medical",
  "controls": [
    {
      "kind": "radio",
      "label": "Male",
      "selected": false,
      "bbox_pt": [
        94,
        598.0,
        14,
        14
      ],
      "parent": "Sex"
    },
    {
      "kind": "radio",
      "label": "Female",
      "selected": false,
      "bbox_pt": [
        174,
        598.0,
        14,
        14
      ],
      "parent": "Sex"
    },
    {
      "kind": "radio",
      "label": "Other",
      "selected": true,
      "bbox_pt": [
        254,
        598.0,
        14,
        14
      ],
      "parent": "Sex"
    },
    {
      "kind": "radio",
      "label": "Yes",
      "selected": false,
      "bbox_pt": [
        174,
        568.0,
        14,
        14
      ],
      "parent": "Smoker"
    },
    {
      "kind": "radio",
      "label": "No",
      "selected": true,
      "bbox_pt": [
        256,
        567.0,
        14,
        14
      ],
      "parent": "Smoker"
    },
    {
      "kind": "checkbox",
      "label": "Yes",
      "selected": true,
      "bbox_pt": [
        174,
        540.0,
        14,
        14
      ],
      "parent": "Diabetic"
    },
    {
      "kind": "checkbox",
      "label": "No",
      "selected": false,
      "bbox_pt": [
        251,
        538.0,
        14,
        14
      ],
      "parent": "Diabetic"
    },
    {
      "kind": "checkbox",
      "label": "Penicillin",
      "selected": false,
      "bbox_pt": [
        54,
        500.0,
        14,
        14
      ]
    },
    {
      "kind": "checkbox",
      "label": "Peanuts",
      "selected": false,
      "bbox_pt": [
        52,
        484.0,
        14,
        14
      ]
    },
    {
      "kind": "checkbox",
      "label": "Latex",
      "selected": false,
      "bbox_pt": [
        53,
        466.0,
        14,
        14
      ]
    },
    {
      "kind": "checkbox",
      "label": "Shellfish",
      "selected": false,
      "bbox_pt": [
        53,
        448.0,
        14,
        14
      ]
    },
    {
      "kind": "checkbox",
      "label": "Pollen",
      "selected": false,
      "bbox_pt": [
        55,
        431.0,
        14,
        14
      ]
    },
    {
      "kind": "checkbox",
      "label": "Dust",
      "selected": false,
      "bbox_pt": [
        52,
        413.0,
        14,
        14
      ]
    },
    {
      "kind": "checkbox",
      "label": "None Known",
      "selected": true,
      "bbox_pt": [
        195,
        504.0,
        14,
        14
      ]
    },
    {
      "kind": "checkbox",
      "label": "Fever",
      "selected": false,
      "bbox_pt": [
        320.0,
        608.0,
        14,
        14
      ]
    },
    {
      "kind": "checkbox",
      "label": "Cough",
      "selected": false,
      "bbox_pt": [
        318.0,
        592.0,
        14,
        14
      ]
    },
    {
      "kind": "checkbox",
      "label": "Headache",
      "selected": false,
      "bbox_pt": [
        318.0,
        573.0,
        14,
        14
      ]
    },
    {
      "kind": "checkbox",
      "label": "Fatigue",
      "selected": false,
      "bbox_pt": [
        319.0,
        555.0,
        14,
        14
      ]
    },
    {
      "kind": "checkbox",
      "label": "Shortness of breath",
      "selected": false,
      "bbox_pt": [
        317.0,
        534.0,
        14,
        14
      ]
    },
    {
      "kind": "checkbox",
      "label": "Nausea",
      "selected": true,
      "bbox_pt": [
        316.0,
        520.0,
        14,
        14
      ]
    },
    {
      "kind": "checkbox",
      "label": "Dizziness",
      "selected": false,
      "bbox_pt": [
        457.0,
        608.0,
        14,
        14
      ]
    },
    {
      "kind": "checkbox",
      "label": "Chest pain",
      "selected": false,
      "bbox_pt": [
        456.0,
        589.0,
        14,
        14
      ]
    }
  ]
}