{
  "person": {
    "name": "Jamie Johnson",
    "dob": "07/19/1975",
    "phone": "(605) 444-8110",
    "address": [
      "237 Birch Blvd",
      "Springfield, FL 79586"
    ],
    "sex": "Other"
  },
  "meta": {
    "mrn": "191991-92",
    "physician": "Dr. Thomas",
    "emergency_contact": "Avery Smith",
    "emergency_phone": "(838) 758-2977",
    "smoker": true,
    "diabetic": true,
    "allergies": [
      "None Known"
    ],
    "symptoms": [
      2
    ]
  },
  "type": "medical",
  "controls": [
    {
      "kind": "radio",
      "label": "Male",
      "selected": false,
      "bbox_pt": [
        94,
        598.0,
        10,
        10
      ],
      "parent": "Sex"
    },
    {
      "kind": "radio",
      "label": "Female",
      "selected": false,
      "bbox_pt": [
        174,
        598.0,
        10,
        10
      ],
      "parent": "Sex"
    },
    {
      "kind": "radio",
      "label": "Other",
      "selected": true,
      "bbox_pt": [
        254,
        598.0,
        10,
        10
      ],
      "parent": "Sex"
    },
    {
      "kind": "radio",
      "label": "Yes",
      "selected": true,
      "bbox_pt": [
        174,
        568.0,
        10,
        10
      ],
      "parent": "Smoker"
    },
    {
      "kind": "radio",
      "label": "No",
      "selected": false,
      "bbox_pt": [
        254,
        568.0,
        10,
        10
      ],
      "parent": "Smoker"
    },
    {
      "kind": "checkbox",
      "label": "Yes",
      "selected": true,
      "bbox_pt": [
        172,
        540.0,
        11,
        11
      ],
      "parent": "Diabetic"
    },
    {
      "kind": "checkbox",
      "label": "No",
      "selected": false,
      "bbox_pt": [
        252,
        540.0,
        11,
        11
      ],
      "parent": "Diabetic"
    },
    {
      "kind": "checkbox",
      "label": "Penicillin",
      "selected": false,
      "bbox_pt": [
        54,
        502.0,
        11,
        11
      ]
    },
    {
      "kind": "checkbox",
      "label": "Peanuts",
      "selected": false,
      "bbox_pt": [
        54,
        484.0,
        11,
        11
      ]
    },
    {
      "kind": "checkbox",
      "label": "Latex",
      "selected": false,
      "bbox_pt": [
        54,
        466.0,
        11,
        11
      ]
    },
    {
      "kind": "checkbox",
      "label": "Shellfish",
      "selected": false,
      "bbox_pt": [
        54,
        448.0,
        11,
        11
      ]
    },
    {
      "kind": "checkbox",
      "label": "Pollen",
      "selected": false,
      "bbox_pt": [
        54,
        430.0,
        11,
        11
      ]
    },
    {
      "kind": "checkbox",
      "label": "Dust",
      "selected": false,
      "bbox_pt": [
        54,
        412.0,
        11,
        11
      ]
    },
    {
      "kind": "checkbox",
      "label": "None Known",
      "selected": true,
      "bbox_pt": [
        194,
        502.0,
        11,
        11
      ]
    },
    {
      "kind": "checkbox",
      "label": "Fever",
      "selected": false,
      "bbox_pt": [
        318.0,
        608.0,
        11,
        11
      ]
    },
    {
      "kind": "checkbox",
      "label": "Cough",
      "selected": false,
      "bbox_pt": [
        318.0,
        590.0,
        11,
        11
      ]
    },
    {
      "kind": "checkbox",
      "label": "Headache",
      "selected": true,
      "bbox_pt": [
        318.0,
        572.0,
        11,
        11
      ]
    },
    {
      "kind": "checkbox",
      "label": "Fatigue",
      "selected": false,
      "bbox_pt": [
        318.0,
        554.0,
        11,
        11
      ]
    },
    {
      "kind": "checkbox",
      "label": "Shortness of breath",
      "selected": false,
      "bbox_pt": [
        318.0,
        536.0,
        11,
        11
      ]
    },
    {
      "kind": "checkbox",
      "label": "Nausea",
      "selected": false,
      "bbox_pt": [
        318.0,
        518.0,
        11,
        11
      ]
    },
    {
      "kind": "checkbox",
      "label": "Dizziness",
      "selected": false,
      "bbox_pt": [
        458.0,
        608.0,
        11,
        11
      ]
    },
    {
      "kind": "checkbox",
      "label": "Chest pain",
      "selected": false,
      "bbox_pt": [
        458.0,
        590.0,
        11,
        11
      ]
    }
  ]
}