{
  "person": {
    "name": "Morgan Martin",
    "dob": "01/19/1944",
    "phone": "(509) 744-6870",
    "address": [
      "224 Pine Rd",
      "Greenville, AZ 64786"
    ],
    "sex": "Male"
  },
  "meta": {
    "policy_id": "F1817871",
    "ins_type": "HMO",
    "work_related": true,
    "auto_accident": true,
    "claim_type": "Procedure"
  },
  "type": "insurance",
  "controls": [
    {
      "kind": "radio",
      "label": "Yes",
      "selected": true,
      "bbox_pt": [
        171,
        617.0,
        12,
        12
      ],
      "parent": "Is this work-related?"
    },
    {
      "kind": "radio",
      "label": "No",
      "selected": false,
      "bbox_pt": [
        251,
        613.0,
        12,
        12
      ],
      "parent": "Is this work-related?"
    },
    {
      "kind": "checkbox",
      "label": "Yes",
      "selected": true,
      "bbox_pt": [
        174,
        585.0,
        13,
        13
      ],
      "parent": "Auto accident?"
    },
    {
      "kind": "checkbox",
      "label": "No",
      "selected": false,
      "bbox_pt": [
        250,
        590.0,
        13,
        13
      ],
      "parent": "Auto accident?"
    },
    {
      "kind": "radio",
      "label": "Visit",
      "selected": false,
      "bbox_pt": [
        320.0,
        628.0,
        12,
        12
      ],
      "parent": "Claim Type"
    },
    {
      "kind": "radio",
      "label": "Procedure",
      "selected": true,
      "bbox_pt": [
        320.0,
        610.0,
        12,
        12
      ],
      "parent": "Claim Type"
    },
    {
      "kind": "radio",
      "label": "Medication",
      "selected": false,
      "bbox_pt": [
        320.0,
        592.0,
        12,
        12
      ],
      "parent": "Claim Type"
    },
    {
      "kind": "radio",
      "label": "Other",
      "selected": false,
      "bbox_pt": [
        320.0,
        574.0,
        12,
        12
      ],
      "parent": "Claim Type"
    },
    {
      "kind": "checkbox",
      "label": "X-Ray",
      "selected": false,
      "bbox_pt": [
        318.0,
        542.0,
        13,
        13
      ]
    },
    {
      "kind": "checkbox",
      "label": "MRI",
      "selected": false,
      "bbox_pt": [
        316.0,
        529.0,
        13,
        13
      ]
    },
    {
      "kind": "checkbox",
      "label": "Lab Work",
      "selected": true,
      "bbox_pt": [
        318.0,
        510.0,
        13,
        13
      ]
    },
    {
      "kind": "checkbox",
      "label": "Physical Therapy",
      "selected": true,
      "bbox_pt": [
        320.0,
        489.0,
        13,
        13
      ]
    },
    {
      "kind": "checkbox",
      "label": "Consultation",
      "selected": false,
      "bbox_pt": [
        320.0,
        472.0,
        13,
        13
      ]
    },
    {
      "kind": "checkbox",
      "label": "Surgery",
      "selected": true,
      "bbox_pt": [
        319.0,
        456.0,
        13,
        13
      ]
    }
  ]
}